za_parliament_scrapers/__init__.py
za_parliament_scrapers/questions.py
za_parliament_scrapers-0.1.0.dist-info/DESCRIPTION.rst
za_parliament_scrapers-0.1.0.dist-info/METADATA
za_parliament_scrapers-0.1.0.dist-info/metadata.json
za_parliament_scrapers-0.1.0.dist-info/RECORD
za_parliament_scrapers-0.1.0.dist-info/top_level.txt
za_parliament_scrapers-0.1.0.dist-info/WHEEL
